permutation_feature_selector/__init__.py
permutation_feature_selector/permutation_feature_selector.py
permutation_feature_selector-0.2.4.dist-info/licenses/LICENSE
permutation_feature_selector-0.2.4.dist-info/METADATA
permutation_feature_selector-0.2.4.dist-info/WHEEL
permutation_feature_selector-0.2.4.dist-info/top_level.txt
permutation_feature_selector-0.2.4.dist-info/RECORD
